pykaban/__init__.py
pykaban/_utils.py
pykaban/cli.py
pykaban/exceptions.py
pykaban/pykaban.py
pykaban/version.py
pykaban-0.5.0.dist-info/METADATA
pykaban-0.5.0.dist-info/RECORD
pykaban-0.5.0.dist-info/WHEEL
pykaban-0.5.0.dist-info/entry_points.txt
pykaban-0.5.0.dist-info/top_level.txt
