Metadata-Version: 2.1
Name: pykaban
Version: 0.5.0
Summary: A Python client for Azkaban AJAX API with lite enhancement.Developed by xiaoshuai.
Home-page: https://github.com/xiaoshuai/pykaban
Author: xiaoshuai
Author-email: qixiaoshuai@outlook.com
License: MIT
Platform: UNKNOWN
Classifier: License :: OSI Approved :: MIT License
Classifier: Programming Language :: Python :: 2.7
Classifier: Programming Language :: Python :: 3.6
Classifier: Topic :: System :: Monitoring
Requires-Dist: click (>=6.1)
Requires-Dist: requests (>=2.12.5)
